bonito/__init__.py
bonito/__main__.py
bonito/aligner.py
bonito/data.py
bonito/io.py
bonito/multiprocessing.py
bonito/nn.py
bonito/pod5.py
bonito/reader.py
bonito/schedule.py
bonito/training.py
bonito/util.py
bonito/cli/__init__.py
bonito/cli/basecaller.py
bonito/cli/download.py
bonito/cli/duplex.py
bonito/cli/evaluate.py
bonito/cli/export.py
bonito/cli/train.py
bonito/cli/view.py
bonito/crf/__init__.py
bonito/crf/basecall.py
bonito/crf/model.py
bonito/ctc/__init__.py
bonito/ctc/basecall.py
bonito/ctc/model.py
bonito/data/README.md
bonito/models/README.md
bonito/models/configs/dna_r9.4.1@v1.toml
bonito/models/configs/dna_r9.4.1@v2.toml
bonito/models/configs/dna_r9.4.1@v3.toml
bonito/transformer/__init__.py
bonito/transformer/basecall.py
bonito/transformer/model.py
ont_bonito-1.0.1.dist-info/licenses/LICENCE.txt
test/__init__.py
test/test_cli.py
test/test_download.py
ont_bonito-1.0.1.dist-info/METADATA
ont_bonito-1.0.1.dist-info/WHEEL
ont_bonito-1.0.1.dist-info/entry_points.txt
ont_bonito-1.0.1.dist-info/top_level.txt
ont_bonito-1.0.1.dist-info/RECORD
