Metadata-Version: 2.4
Name: ont-bonito
Version: 1.0.1
Author-email: "Oxford Nanopore Technologies, Ltd" <support@nanoporetech.com>
Project-URL: Homepage, https://github.com/nanoporetech/bonito
Requires-Python: >=3.10
License-File: LICENCE.txt
Requires-Dist: edlib
Requires-Dist: fast-ctc-decode
Requires-Dist: mappy
Requires-Dist: numpy
Requires-Dist: pandas
Requires-Dist: parasail
Requires-Dist: pod5
Requires-Dist: pysam
Requires-Dist: python-dateutil
Requires-Dist: requests
Requires-Dist: toml
Requires-Dist: tqdm
Requires-Dist: wheel
Requires-Dist: torch~=2.9
Requires-Dist: ont-koi==0.6.5
Provides-Extra: cu128
Requires-Dist: torch==2.9.1+cu128; extra == "cu128"
Provides-Extra: cu130
Requires-Dist: torch==2.9.1+cu130; extra == "cu130"
Dynamic: license-file
